hello_world/__init__.py
hello_world/main.py
hello_world/model/task.py
hello_world/services/tasks_service.py
jesseprusso_hello_world_lib-0.1.0.dist-info/METADATA
jesseprusso_hello_world_lib-0.1.0.dist-info/WHEEL
jesseprusso_hello_world_lib-0.1.0.dist-info/top_level.txt
jesseprusso_hello_world_lib-0.1.0.dist-info/RECORD
