Metadata-Version: 2.4
Name: jesseprusso-hello-world-lib
Version: 0.1.0
Summary: Uma biblioteca simples para gerenciar tarefas
Author-email: Jessé <jesseprusso@gmail.com>
Project-URL: Homepage, https://github.com/seu_usuario/hello-world-lib
Requires-Python: >=3.7
